egg_smol-0.3.1.dist-info/METADATA
egg_smol-0.3.1.dist-info/WHEEL
egg_smol-0.3.1.dist-info/license_files/LICENSE
egg_smol/type_constraint_solver.py
egg_smol/bindings.pyi
egg_smol/monkeypatch.py
egg_smol/examples/lambda.py
egg_smol/examples/eqsat_basic.py
egg_smol/examples/matrix.py
egg_smol/examples/README.rst
egg_smol/examples/__init__.py
egg_smol/examples/resolution.py
egg_smol/py.typed
egg_smol/declarations.py
egg_smol/__init__.py
egg_smol/egraph.py
egg_smol/config.py
egg_smol/runtime.py
egg_smol/builtins.py
egg_smol/bindings.pypy37-pp73-x86_64-linux-gnu.so
egg_smol-0.3.1.dist-info/RECORD
