Metadata-Version: 2.1
Name: egg-smol
Version: 0.3.1
Classifier: Environment :: MacOS X
Classifier: Environment :: Win32 (MS Windows)
Classifier: Intended Audience :: Developers
Classifier: License :: OSI Approved :: MIT License
Classifier: Natural Language :: English
Classifier: Programming Language :: Python :: 3
Classifier: Programming Language :: Python :: 3.8
Classifier: Programming Language :: Python :: 3.9
Classifier: Programming Language :: Python :: 3.10
Classifier: Programming Language :: Python :: 3.11
Classifier: Programming Language :: Rust
Classifier: Programming Language :: Python :: Implementation :: CPython
Classifier: Programming Language :: Python :: Implementation :: PyPy
Classifier: Topic :: Software Development :: Compilers
Classifier: Topic :: Software Development :: Interpreters
Classifier: Typing :: Typed
Requires-Dist: typing-extensions
Requires-Dist: black
Requires-Dist: pydata-sphinx-theme; extra == 'docs'
Requires-Dist: myst-nb; extra == 'docs'
Requires-Dist: sphinx-autodoc-typehints; extra == 'docs'
Requires-Dist: sphinx-gallery; extra == 'docs'
Requires-Dist: matplotlib; extra == 'docs'
Requires-Dist: pre-commit; extra == 'dev'
Requires-Dist: black; extra == 'dev'
Requires-Dist: mypy; extra == 'dev'
Requires-Dist: flake8; extra == 'dev'
Requires-Dist: isort; extra == 'dev'
Requires-Dist: pytest; extra == 'test'
Requires-Dist: mypy; extra == 'test'
Provides-Extra: docs
Provides-Extra: dev
Provides-Extra: test
License-File: LICENSE
Summary: e-graphs in Python built around the the egg-smol rust library
License: MIT
Requires-Python: >=3.7
